{
  "1398": "Computadores",
  "1399": "Ofertas",
  "1400": "Gaming",
  "1407": "Smartphones",
  "1408": "Productos Nuevos",
  "1412": "Smartphones &amp; Tablets",
  "1414": "Mas Vendidos",
  "1418": "Viewed Product",
  "1432": "Accesorios",
  "1433": "Portatiles",
  "1434": "Escritorio",
  "1454": "Diademas",
  "1455": "Auriculares",
  "1456": "Camaras",
  "1457": "Mouse",
  "1458": "Teclados",
  "1477": "Impresoras",
  "1478": "Impresoras Laser",
  "1479": "Impresoras de Tinta",
  "1480": "Impresoras Multifuncion",
  "1503": "Monitores",
  "1612": "Televisores",
  "1613": "Smart Home",
  "1619": "Proyectores",
  "1641": "Iluminaci\u00f3n",
  "1670": "Smartwatch",
  "1671": "SmartWatch",
  "1677": "Audio",
  "1762": "Sin categorizar"
}